LICENSE.txt
MANIFEST.in
README.rst
setup.cfg
setup.py
pydiffusion/Dtools.py
pydiffusion/__init__.py
pydiffusion/core.py
pydiffusion/io.py
pydiffusion/plot.py
pydiffusion/simulation.py
pydiffusion/smooth.py
pydiffusion/utils.py
pydiffusion.egg-info/PKG-INFO
pydiffusion.egg-info/SOURCES.txt
pydiffusion.egg-info/dependency_links.txt
pydiffusion.egg-info/requires.txt
pydiffusion.egg-info/top_level.txt