Metadata-Version: 1.2
Name: pydiffusion
Version: 0.2.1
Summary: A Python library for diffusion simulation and data analysis
Home-page: https://github.com/zhangqi-chen/pyDiffusion
Author: Zhangqi Chen
Author-email: wshchzhq@gmail.com
License: MIT
Keywords: diffusion,simulation,python
Platform: UNKNOWN
Classifier: Development Status :: 4 - Beta
Classifier: Intended Audience :: Science/Research
Classifier: Topic :: Scientific/Engineering :: Physics
Classifier: Topic :: Scientific/Engineering :: Chemistry
Classifier: License :: OSI Approved :: MIT License
Classifier: Programming Language :: Python :: 3.5
Classifier: Programming Language :: Python :: 3.6
Requires-Python: >=3.5
